[
  {
    "mid": "/m/0k4j",
    "description": "car",
    "score": 0.9854164123535156,
    "topicality": 0.9854164123535156
  },
  {
    "mid": "/m/06gfj",
    "description": "road",
    "score": 0.9766766428947449,
    "topicality": 0.9766766428947449
  },
  {
    "mid": "/m/01prls",
    "description": "land vehicle",
    "score": 0.9742258787155151,
    "topicality": 0.9742258787155151
  },
  {
    "mid": "/m/012f08",
    "description": "motor vehicle",
    "score": 0.968578577041626,
    "topicality": 0.968578577041626
  },
  {
    "mid": "/m/07yv9",
    "description": "vehicle",
    "score": 0.9462131857872009,
    "topicality": 0.9462131857872009
  },
  {
    "mid": "/m/033j3c",
    "description": "lane",
    "score": 0.9377691149711609,
    "topicality": 0.9377691149711609
  },
  {
    "mid": "/m/07bsy",
    "description": "transport",
    "score": 0.909600019454956,
    "topicality": 0.909600019454956
  },
  {
    "mid": "/m/088l6h",
    "description": "family car",
    "score": 0.8946893811225891,
    "topicality": 0.8946893811225891
  },
  {
    "mid": "/m/079bkr",
    "description": "mode of transport",
    "score": 0.8752562999725342,
    "topicality": 0.8752562999725342
  },
  {
    "mid": "/m/017kvv",
    "description": "infrastructure",
    "score": 0.8668513894081116,
    "topicality": 0.8668513894081116
  }
]